mml_invoke/__init__.py
mml_invoke/py.typed
mml_invoke/tasks/__init__.py
mml_invoke/tasks/datascience.py
mml_invoke/tasks/general.py
mml_invoke/tasks/install.py
mml_invoke/utils.py
mml_invoke-0.1.2.dist-info/AUTHORS.md
mml_invoke-0.1.2.dist-info/METADATA
mml_invoke-0.1.2.dist-info/WHEEL
mml_invoke-0.1.2.dist-info/RECORD
